odoo10_addon_account_payment_show_invoice-10.0.1.0.0-py2.7-nspkg.pth
odoo/addons/account_payment_show_invoice/README.rst
odoo/addons/account_payment_show_invoice/__init__.py
odoo/addons/account_payment_show_invoice/__manifest__.py
odoo/addons/account_payment_show_invoice/models/__init__.py
odoo/addons/account_payment_show_invoice/models/account_payment.py
odoo/addons/account_payment_show_invoice/static/description/icon.png
odoo/addons/account_payment_show_invoice/static/description/payments_view.png
odoo/addons/account_payment_show_invoice/views/account_payment_view.xml
odoo10_addon_account_payment_show_invoice-10.0.1.0.0.dist-info/DESCRIPTION.rst
odoo10_addon_account_payment_show_invoice-10.0.1.0.0.dist-info/METADATA
odoo10_addon_account_payment_show_invoice-10.0.1.0.0.dist-info/RECORD
odoo10_addon_account_payment_show_invoice-10.0.1.0.0.dist-info/WHEEL
odoo10_addon_account_payment_show_invoice-10.0.1.0.0.dist-info/metadata.json
odoo10_addon_account_payment_show_invoice-10.0.1.0.0.dist-info/namespace_packages.txt
odoo10_addon_account_payment_show_invoice-10.0.1.0.0.dist-info/top_level.txt
